lemmy2fedi/__init__.py
lemmy2fedi/app.py
lemmy2fedi/config.py
lemmy2fedi/control.py
lemmy2fedi/publish.py
lemmy2fedi-2.0.1.dist-info/METADATA
lemmy2fedi-2.0.1.dist-info/WHEEL
lemmy2fedi-2.0.1.dist-info/entry_points.txt
lemmy2fedi-2.0.1.dist-info/licenses/LICENSE.md
lemmy2fedi-2.0.1.dist-info/RECORD
