Metadata-Version: 2.4
Name: lemmy2fedi
Version: 2.0.1
Summary: Bot to copy posts (including attachments) from lemmy communities to a fediverse account.
Author-email: marvin8 <marvin8@tuta.io>
License: AGPL-3.0-or-later
License-File: LICENSE.md
Classifier: Development Status :: 5 - Production/Stable
Classifier: Programming Language :: Python
Classifier: Programming Language :: Python :: 3.11
Classifier: Programming Language :: Python :: 3.12
Requires-Python: <3.13,>=3.11
Requires-Dist: httpx~=0.28.1
Requires-Dist: loguru~=0.7.3
Requires-Dist: minimal-activitypub>=1.3.1
Requires-Dist: msgspec~=0.18.6
Requires-Dist: stamina~=24.3.0
Requires-Dist: tomli-w~=1.1.0
Requires-Dist: typer~=0.15.1
